elog_cli/__init__.py
elog_cli/auth_manager.py
elog_cli/hl_api.py
elog_cli/main.py
elog_cli/oauth_login.py
elog_cli/token_login.py
elog_cli/commands/__init__.py
elog_cli/commands/common.py
elog_cli/commands/create_entry.py
elog_cli/commands/create_tag.py
elog_cli/commands/get_ngram_stat.py
elog_cli/commands/import_entry.py
elog_cli/commands/list_entries.py
elog_cli/commands/list_logbooks.py
elog_cli/commands/login.py
elog_cli/commands/show_entry.py
elog_cli/commands/show_logbook.py
elog_cli/commands/update_entry_attachments.py
elog_cli/commands/update_ngram.py
elog_cli/commands/update_tag.py
elog_cli/elog_management_backend_client/__init__.py
elog_cli/elog_management_backend_client/client.py
elog_cli/elog_management_backend_client/errors.py
elog_cli/elog_management_backend_client/py.typed
elog_cli/elog_management_backend_client/types.py
elog_cli/elog_management_backend_client/api/__init__.py
elog_cli/elog_management_backend_client/api/application_token_management_v_1/__init__.py
elog_cli/elog_management_backend_client/api/application_token_management_v_1/create_new_application.py
elog_cli/elog_management_backend_client/api/application_token_management_v_1/delete_application.py
elog_cli/elog_management_backend_client/api/application_token_management_v_1/find_all_application.py
elog_cli/elog_management_backend_client/api/application_token_management_v_1/find_application_by_id.py
elog_cli/elog_management_backend_client/api/attachment_management_v_1/__init__.py
elog_cli/elog_management_backend_client/api/attachment_management_v_1/download.py
elog_cli/elog_management_backend_client/api/attachment_management_v_1/download_preview.py
elog_cli/elog_management_backend_client/api/attachment_management_v_1/download_webp_preview.py
elog_cli/elog_management_backend_client/api/attachment_management_v_1/find_all_queued_attachments.py
elog_cli/elog_management_backend_client/api/attachment_management_v_1/get_attachment.py
elog_cli-0.1.40.dist-info/METADATA
elog_cli-0.1.40.dist-info/WHEEL
elog_cli-0.1.40.dist-info/entry_points.txt
elog_cli-0.1.40.dist-info/top_level.txt
elog_cli-0.1.40.dist-info/RECORD
