Metadata-Version: 2.4
Name: elog-cli
Version: 0.1.40
Summary: CLI tool for elog management
Author-email: Claudio Bisegni <bisegni@slac.stanford.edu>
Requires-Python: >=3.10
Requires-Dist: click
Requires-Dist: click-loglevel
Requires-Dist: click_repl
Requires-Dist: pytest
Requires-Dist: requests
Requires-Dist: PyJWT
Requires-Dist: attrs
Requires-Dist: httpx
Requires-Dist: python-dateutil
Requires-Dist: openapi-python-client
